{
    "Normal": [
        "rainbow",
        "reef",
        "jungle ruins",
        "steam train",
        "hot springs",
        "windmill",
        "glacier",
        "caravan",
        "ice cave",
        "giant tree",
        "cliff",
        "tundra",
        "pony pasture",
        "hill tomb",
        "waterfall",
        "desert oasis",
        "bamboo grove",
        "pebble beach",
        "cherry blossom park",
        "pine forest",
        "deep sea trench",
        "volcanic island",
        "sunny meadow",
        "rocky canyon",
        "alpine ski slope",
        "colorful coral reef",
        "city skyline",
        "rainy city street",
        "snowy village",
        "redwood forest",
        "sprawling vineyard",
        "medieval monastery",
        "enchanted forest",
        "floating islands",
        "magical waterfall",
        "sunflower field",
        "ancient ruins",
        "crystal clear lake",
        "secret garden",
        "enchanted cavern",
        "starry night sky",
        "enchanted castle",
        "fairy circle",
        "mystical floating city",
        "sunset over the ocean",
        "underwater kingdom",
        "enchanted waterfall",
        "lush oasis",
        "hidden cave",
        "enchanted glade",
        "moonlit beach",
        "majestic mountains",
        "mysterious foggy forest",
        "hidden waterfall",
        "peaceful river",
        "sunrise over the mountains",
        "enchanted meadow",
        "ancient tree",
        "enchanted lake",
        "fiery sunset",
        "starry meadow",
        "enchanted bridge",
        "peaceful countryside",
        "ancient temple",
        "enchanted garden",
        "serene forest",
        "sunflower meadow",
        "enchanted island",
        "tranquil bay",
        "whimsical treehouse",
        "enchanted well",
        "serene waterfall",
        "starry sky",
        "enchanted village",
        "tranquil pond",
        "whimsical garden",
        "enchanted forest",
        "serene beach",
        "sunlit meadow",
        "enchanted river",
        "tranquil garden",
        "whimsical village",
        "enchanted mountain",
        "serene lake"
    ],
    "Futuristic": [
        "hyperloop station",
        "spaceport",
        "fusion power plant",
        "orbital colony",
        "astrophysics lab",
        "quantum computer factory",
        "nuclear fusion cityscape",
        "plasma waterfall",
        "robot pets park",
        "extraterrestrial botanical garden",
        "wormhole",
        "nano-tech city",
        "cybernetic arena",
        "hoverboard race track",
        "stellar cruise ship",
        "virtual reality theme park",
        "holographic cityscape",
        "unmanned drone hive",
        "artificial intelligence research facility",
        "magnetic levitation train"
    ],
    "Planets": [
        "Alpha Centauri",
        "Andromeda",
        "Kepler-452b",
        "Proxima b",
        "Betelgeuse",
        "Vega",
        "Tatooine",
        "Hoth",
        "Endor",
        "Naboo",
        "Alderaan",
        "Dagobah",
        "Krypton",
        "Pandora",
        "Pern",
        "Gaia",
        "Cybertron",
        "Nibiru",
        "Gallifrey",
        "Io",
        "Utopia",
        "Elysium",
        "Exodus",
        "Avalon",
        "Ravenna",
        "Zephyr",
        "Prysmos",
        "Eternia",
        "Skaro",
        "Atlantis",
        "Olympus",
        "Valhalla"
    ],
    "Fantasy": [
        "mermaid lagoon",
        "phoenix roost",
        "nymph village",
        "werewolf lair",
        "genie bottle",
        "enchanted corn maze",
        "crystal palace",
        "giant's beanstalk",
        "witch's gingerbread house",
        "ghost town",
        "fairy-tale castle",
        "troll bridge",
        "gnome village",
        "sorcerer's study",
        "angel cloud city",
        "dragon's lair",
        "elf kingdom",
        "magic mirror",
        "enchanted forest",
        "unicorn meadow",
        "fountain of youth",
        "wizard's tower",
        "dwarf mine",
        "centaur plains",
        "pegasus sanctuary",
        "enchanted river",
        "griffin's nest",
        "mystical waterfall",
        "pixie hollow",
        "feywild",
        "troll's cave",
        "gnomish workshop",
        "siren cove",
        "faun's grove",
        "mystic temple",
        "celestial realm"
    ],
    "Prehistoric": [
        "pterodactyl peak",
        "triassic desert",
        "neanderthal camp",
        "woolly mammoth tundra",
        "dinosaur stampede",
        "early human cave painting",
        "sabertooth canyon",
        "prehistoric jungle",
        "megafauna habitat",
        "arctic dinosaur encampment",
        "prehistoric ocean",
        "volcanic dinosaur nesting grounds",
        "prehistoric mountain range",
        "prehistoric river delta",
        "prehistoric island",
        "prehistoric rainforest",
        "ice age haven",
        "prehistoric volcano",
        "prehistoric waterfall",
        "prehistoric marshland",
        "prehistoric savannah",
        "cave lion's den",
        "prehistoric oasis",
        "prehistoric steppe",
        "prehistoric reef",
        "prehistoric countryside",
        "prehistoric lake",
        "prehistoric desert",
        "prehistoric glacier",
        "prehistoric forest"
    ],
    "Mythological": [
        "Loch Ness",
        "Area 51",
        "Bifröst Bridge",
        "Stonehenge",
        "the Labyrinth",
        "Cyclops Island",
        "Pegasus Stable",
        "Medusa's Lair",
        "Fountain of Youth",
        "Odin’s Throne",
        "Zombie Graveyard",
        "Yeti's Den",
        "Bigfoot's Forest",
        "Chupacabra's Caves",
        "Mount Olympus",
        "Shangri-La",
        "El Dorado",
        "Asgard",
        "Avalon",
        "Agartha",
        "Hyperborea",
        "Tír na nÓg",
        "Camelot",
        "Niflheim",
        "Vanaheim",
        "Jotunheim",
        "Helheim",
        "Alfheim",
        "Svartalfheim",
        "Muspelheim"
    ],
    "Extraterrestrial": [
        "space nebula",
        "star cluster",
        "Galactic Core",
        "lunar base",
        "space-time rift",
        "alien savannah",
        "alien sky city",
        "alien ice world",
        "crater colony",
        "alien fungi forest",
        "navigational beacon",
        "interstellar trading post",
        "celestial garden",
        "cosmic carnival",
        "alien research facility",
        "extraterrestrial marketplace",
        "astral projection realm",
        "intelligent plant species sanctuary",
        "extraterrestrial zoo",
        "alien artifact dig site",
        "cosmic energy harvesting station",
        "intergalactic transportation hub",
        "exo-planet surface exploration",
        "galaxy-wide internet hub",
        "alien insect hive",
        "interdimensional portal",
        "celestial observation deck",
        "cosmic phenomenon sanctuary",
        "alien skywalk",
        "interstellar mining operation",
        "celestial energy harvesting field"
    ],
    "FutureTech": [
        "augmented reality arcade",
        "3D printed city",
        "solar farm",
        "transhumanist society",
        "underwater data center",
        "teleportation hub",
        "holographic concert",
        "time travel institute",
        "deep learning center",
        "artificial intelligence metropolis",
        "biotech research lab",
        "nanotechnology manufacturing facility",
        "neural interface facility",
        "bionic enhancement clinic",
        "cybernetic modification spa",
        "quantum communication network",
        "virtual reality training center",
        "smart city",
        "blockchain hub",
        "self-driving vehicle testing city",
        "drones delivery system",
        "renewable energy power grid",
        "flying car transportation system",
        "genetic engineering research lab",
        "robotics factory",
        "space colonization headquarters",
        "hoverboard testing facility",
        "artificial intelligence ethics committee",
        "cyberspace hub",
        "biometric security facility",
        "quantum teleportation research facility",
        "advanced robotics academy",
        "artificial intelligence-generated music studio",
        "genomic editing research lab"
    ],
    "Ruins": [
        "submerged submarine",
        "crashed UFO",
        "haunted theater",
        "abandoned hospital",
        "viking ruins",
        "egyptian pyramid",
        "mayan temple",
        "sunken ship",
        "dilapidated lighthouse",
        "forbidden catacombs",
        "ancient colosseum",
        "lost civilization ruins",
        "crumbling castle",
        "decaying mansion",
        "deserted prison",
        "forgotten cathedral",
        "derelict factory",
        "ruined citadel",
        "collapsed bridge",
        "overgrown cemetery",
        "drowned village",
        "wrecked spaceship",
        "neglected mansion",
        "ruined library",
        "burnt-out ruins",
        "collapsed tunnel",
        "overgrown temple",
        "crumbling observatory",
        "destroyed fortress",
        "neglected amusement park",
        "ruined abbey",
        "forgotten bunker",
        "ruined courthouse",
        "abandoned insane asylum",
        "neglected orphanage",
        "ruined stadium",
        "collapsed skyscraper",
        "deserted school",
        "forgotten windmill",
        "ruined chapel",
        "abandoned fairground",
        "neglected zoo",
        "ruined monolith",
        "crumbling dam",
        "deserted shopping mall",
        "forgotten laboratory",
        "neglected playground",
        "ruined mansion",
        "abandoned theme park",
        "forgotten mine",
        "rusty shipwreck",
        "crumbling tower",
        "forgotten military base",
        "neglected factory",
        "ruined amphitheater",
        "collapsed cave"
    ],
    "Abstract": [
        "fractal forest",
        "geometric city",
        "neon jungle",
        "surreal sky",
        "cubist mountain",
        "impossible staircase",
        "non-euclidean geometry world",
        "kaleidoscope landscape",
        "polychrome plains",
        "mobius strip city",
        "infinity mirror room",
        "dreamscape",
        "abstract art gallery",
        "reality-bending labyrinth",
        "ethereal realm",
        "psychedelic garden",
        "otherworldly dimension",
        "futuristic metropolis",
        "mind-bending maze",
        "dystopian cityscape",
        "hyperrealistic dreamscape",
        "illusionary skyline",
        "trippy kaleidoscope",
        "hypnotic light installation",
        "mind-altering space",
        "surrealistic wonderland",
        "metaphysical vortex",
        "virtual reality universe",
        "abstract sculpture garden",
        "illusory landscape",
        "quantum reality",
        "mysterious droste effect",
        "disorienting cubist landscape",
        "unsettling glitched city",
        "perplexing optical illusion",
        "vibrant abstract mural",
        "alternate reality realm",
        "imagination-fueled dimension",
        "hypnagogic tapestry",
        "fantastical color spectrum"
    ],
    "Historical": [
        "WWII battlefield",
        "Victorian London",
        "1920s New York",
        "ancient Rome",
        "feudal Japan",
        "Egyptian pyramid construction",
        "Greek amphitheater",
        "Viking long ship",
        "1950s diner",
        "Wild West",
        "Ancient Chinese city",
        "Aztec Empire",
        "Medieval castle",
        "prehistoric cave paintings",
        "Stone Age settlement",
        "Ming Dynasty palace",
        "Renaissance city",
        "Industrial Revolution factory",
        "Ancient Greek marketplace",
        "Mayan civilization",
        "Mughal Empire",
        "Incan ruins",
        "Ancient Persian city",
        "Spartan battleground",
        "Roaring Twenties speakeasy",
        "Ancient Babylon",
        "Viking raiding village",
        "Samurai training ground",
        "Roman gladiator arena",
        "Victorian steampunk laboratory",
        "American Civil War battlefield",
        "Ancient Egyptian obelisk",
        "Edo period market street",
        "Mesoamerican pyramid",
        "Elizabethan theater",
        "Roman bathhouse",
        "Ancient Greek temple",
        "Industrial Revolution train station",
        "Wild West saloon",
        "Feudal European castle",
        "Ancient Arabian souk",
        "Mayan jungle city",
        "Viking burial mound",
        "Ancient Celtic settlement",
        "Ming Dynasty garden",
        "Medieval marketplace",
        "Incan terrace farming",
        "Ancient Persian palace",
        "Aztec sacrificial temple",
        "Egyptian tomb excavation",
        "Mughal mausoleum",
        "Ancient Greek agora"
    ],
    "FantasyRealms": [
        "Floating Crystal Isles",
        "Dwarven Forges Beneath Mount Molten",
        "Eternal Twilight Garden",
        "Luminous Fae Wildwoods",
        "Arcane University Above the Clouds",
        "Goblin King's Underground Labyrinth",
        "Celestial Valkyrie Citadel",
        "Wizarding School of Enchantment",
        "Elven Tree City of the Moon",
        "Haunted Wraithswamp",
        "Enchanted Griffin Aerie",
        "Pegasus Sky Sanctuary",
        "Mystical Unicorn Meadow",
        "Dragon's Roost",
        "Fey-touched Spring Paradise",
        "Troll-infested Mountain Range",
        "Giant's Hidden Valley",
        "Fairy Queen's Jewel Palace",
        "Gnome Hamlet of Glimmering Lanterns",
        "Enchanted Mermaid Cove",
        "Elven Forest Kingdom"
    ],
    "WitchEnclaves": [
        "Elderwood Oracle's Grove",
        "Bewitched Bayou Shack",
        "Cauldron Cavern Network",
        "Skyward Spellcaster Towers",
        "Enchanted Forest Cottage Cluster",
        "Moonlit Witches' Spires",
        "Grimoire Library of Shadows",
        "Hexbound Witch Circle",
        "Mystic Crystal Ball Parlor",
        "Whispering Willow Witch Village",
        "Spellbinding Sorceress Sanctuary",
        "Coven Gathering Grounds",
        "Potion Brewing Alchemist's Den",
        "Moonbeam Enchantment Glade",
        "Hexed Witching Market"
    ],
    "CyberpunkCities": [
        "Neon Nexus Metropolis",
        "Augmented Alleyways",
        "Tech Haven Undercity",
        "Hacker's Hideout in Data District",
        "Monolithic Mega Corporations",
        "Skyward Slums with Hovercars",
        "Cybernetic Central Hub",
        "Dystopian Megacity",
        "Rogue AI-Controlled Skyscrapers",
        "Holographic Billboard-filled Streets",
        "Cybernetic Enhancement Clinics",
        "Underground Market for Illegal Cyberware",
        "Virtual Reality Clubs",
        "Drone-filled Sky Lanes",
        "Cybernetic Underground Crime Syndicate",
        "Future Noir Cityscape",
        "Robotic Law Enforcement Headquarters",
        "Cyberpunk Night Market",
        "Tech Mogul Penthouse",
        "Bioluminescent Cyber Jungle",
        "Dystopian Apartment Complex"
    ],
    "InterstellarLocales": [
        "Gas Giant Mining Platforms",
        "Asteroid Belt Settlement",
        "Terraformed Martian Canyons",
        "Abandoned Space Megastructures",
        "Stellar Observatory Outposts",
        "Cosmic Dust Taverns",
        "Interstellar Communication Array",
        "Exoplanetary Research Outpost",
        "Lunar Mining Colony",
        "Celestial Energies Harvesting Facility",
        "Hyperwarp Gateway Station",
        "Interstellar Cargo Transport Hub",
        "Space Elevator Terminus",
        "Astronaut Training Facility",
        "Exoplanet Zoo",
        "Stellar Nursery",
        "Celestial Energy Refining Plant",
        "Interstellar Trading Port",
        "Zero Gravity Sports Arena",
        "Astrobiology Research Station",
        "Cosmic Dust Cloud",
        "Interstellar Spacewalk Supply Depot",
        "Space Debris Recycling Center",
        "Astronaut Bar and Lounge",
        "Exoplanet Weather Research Facility",
        "Stellar Navigation Academy",
        "Celestial Teleportation Relay",
        "Interstellar Emergency Medical Center",
        "Space Debris Cleanup Crew Station",
        "Astronaut Academy",
        "Astrophotography Observatory",
        "Stellar Archaeology Site",
        "Celestial Energy Shield Generator",
        "Interstellar Rest Stop",
        "Space Debris Tracking Facility"
    ],
    "TechUtopias": [
        "Virtual Paradise Simulation",
        "AI-Run Commune",
        "Genetic Engineering Eden",
        "Quantum Computing Nexus",
        "Sustainable Eco-Tech Sanctuaries",
        "Magnetic Levitation Cities",
        "Solar-Powered Sky Garden",
        "Biodegradable Techno-City",
        "Neurotech Research Institute",
        "Self-Sufficient Eco-Village",
        "Robotic Workforce Paradise",
        "Automation-Controlled Greenhouse",
        "Smart Home City",
        "Advanced Medicine Research Facility",
        "Biotech Enhanced Society",
        "Renewable Energy Power Grid",
        "Aquaponic Vertical Farming City",
        "Genetic Enhancement Clinic",
        "Circular Economy Metropolis",
        "Eco-Friendly Transportation Network",
        "Renewable Energy Infrastructure",
        "Artificial Intelligence Governance Tower",
        "Smart Grid-enabled City",
        "Biohacking Laboratory",
        "Sustainable Waste Management System",
        "Renewable Energy Research Center",
        "Smart Energy Community",
        "Self-Sustaining Solar Community",
        "Artificial Intelligence Algorithm Research",
        "Agritech Farming Community",
        "Eco-Responsible Housing Complex",
        "Sustainable Transportation Hub",
        "Bioenergy Research Facility",
        "Green Technology Showcase",
        "Smart Living Experiment",
        "Vertical Farming Tower",
        "Circular Housing Community",
        "Sustainable Urban Development",
        "Advanced Battery Manufacturing Plant",
        "Renewable Energy Innovation Center",
        "Eco-Tourism Destination",
        "Smart Home Living Community",
        "Smart Sensor City",
        "Advanced Waste-to-Energy Plant",
        "Renewable Energy Education Center",
        "Eco-Design Innovations Hub"
    ],
    "PortalsAndDimensions": [
        "Portal to another dimension",
        "Stargate",
        "Wormhole",
        "Interdimensional Rift",
        "Time Portal",
        "Dimensional Doorway",
        "Interdimensional Gateway",
        "Time Vortex"
    ],
    "MageAcademies": [
        "Conjuror's Collegiate Spire",
        "Summoner's Elemental Grounds",
        "Diviner's Observatory",
        "Enchanter's Alchemical Lab",
        "Illusionist's Hall of Mirrors",
        "Chronomancer's Timeless Library",
        "School of Elemental Magic",
        "Arcane Arts Academy",
        "Transmutation Workshop",
        "Necromancer's Crypt",
        "Alchemy Research Institute",
        "Illusionary Theatre of Magic",
        "School of Celestial Conjuration",
        "School of Shadow Manipulation",
        "Magic Creation Lab",
        "Divination Tablet Library",
        "School of Enchantment",
        "Elemental Mage's Training Grounds",
        "School of Mind Control",
        "Mystical Energy Nexus",
        "School of Abjuration",
        "School of Technomancy",
        "School of Bardic Magic",
        "Mystic Crystal Ball Grotto",
        "School of Astral Projection",
        "School of Planar Magic",
        "School of Mysticism",
        "School of Rune Magic",
        "School of Elemental Evocation",
        "School of Arcane Knowledge",
        "School of Telekinesis",
        "School of Spellwriting",
        "School of Illusory Magic",
        "School of Elemental Transmutation",
        "School of Shadow Conjuration",
        "School of Potions and Elixirs",
        "School of Magical Creatures",
        "School of Elemental Manipulation",
        "School of Metamagic",
        "School of Warding",
        "School of Alchemical Reagents",
        "School of Runesmithing",
        "School of Spirit Conjuration",
        "School of Psionics",
        "School of Spellbreaking",
        "School of Elemental Fusion",
        "School of Puppeteering",
        "School of Summoning",
        "School of Elemental Absorption",
        "School of Shapeshifting",
        "School of Elemental Infusion",
        "School of Pyromancy",
        "School of Verbal Spellcasting",
        "School of Illusory Realms",
        "School of Time Manipulation",
        "School of Spatial Distortion",
        "School of Astral Projection",
        "School of Divination",
        "School of Ancestral Magic",
        "School of Elemental Channeling",
        "School of Spiritual Magic",
        "School of Glyph Magic",
        "School of Crystallomancy",
        "School of Astral Projection",
        "School of Planar Travel",
        "School of Wizardry"
    ],
    "FuturisticArena": [
        "Holo-Gladiator Coliseum",
        "Zero-Gravity Sports Complex",
        "Quantum Dueling Fields",
        "Cyber Jousting Arenas",
        "Telekinetic Battle Rings",
        "Virtual Combat Zones",
        "Battle Bot Arena",
        "Superpowered Arena",
        "Mech Combat Stadium",
        "VR Sports Arena",
        "Laser Tag Stadium",
        "Zero-G Dance Dome",
        "Interdimensional Battle Arena",
        "AI Versus Human Tournament",
        "Intergalactic Racing Track",
        "Cosmic Martial Arts Dojo",
        "Battle of the Bands Stadium",
        "Robotic Sumo Ring",
        "Magic Vs Technology Arena",
        "Future Gladiator Arena",
        "Psychedelic Disco Dome",
        "Giant Robot Fighting Arena",
        "Augmented Reality Football Stadium",
        "Holographic Boxing Ring",
        "Retro Arcade Arena",
        "Virtual Parkour Course",
        "Swordfighting Arena",
        "Drone Racing Track",
        "Futuristic Go-Kart Circuit",
        "Planetary Paintball Arena",
        "Superhero Showdown Arena",
        "Teleportation Arena",
        "Mech Suit Battle Arena",
        "Gravitational Anomaly Arena",
        "Virtual Reality Stealth Mission",
        "Laser Archery Arena",
        "Robotic Arm Wrestling Ring",
        "Cyborg Gladiator Stadium",
        "Powerlifting Arena",
        "Telekinetic Gladiator Arena",
        "Virtual Sailing Race",
        "High-Tech Chess Arena",
        "Mechanical Bull Riding Arena",
        "AI Vs Human Chess Match",
        "Thunderdome",
        "Starship Battle Arena",
        "Telepathic Gladiator Ring",
        "Futuristic Sumo Wrestling Arena",
        "Nano-Scale Combat Arena",
        "Giant Inflatable Gladiator Arena",
        "Battle of the DJs Stadium",
        "Light Saber Dueling Arena",
        "Dystopian Battle Arena",
        "Cybernetic Race Track"
    ],
    "ForbiddenTechnologies": [
        "Cloaked Island of Rogue AI",
        "Sunken Submarines with Forbidden Tech",
        "Hidden Valley of Immortality Machines",
        "Lost City with Time-Altering Devices",
        "Mountain Fortress of Climate Control",
        "Underground Laboratory of Biological Hybrids",
        "Forbidden Nanotechnology Lab",
        "Temporal Manipulation Facility",
        "Reality-Bending Atomic Collider",
        "Black Market Cybernetics District",
        "Forbidden Genetic Engineering Lab",
        "Ancient Artifact Research Facility",
        "Interceptor Drone Manufacturing Plant",
        "Forbidden Energy Amplification Chamber",
        "Underground Robotics Assembly Line",
        "Cloning and Mind Transfer Facility",
        "Forbidden Quantum Computing Facility",
        "Dark Matter Extraction Facility",
        "Forbidden Holography Lab",
        "Viral Weapon Creation Lab",
        "Forbidden Bioweapon Storage Facility",
        "Hidden Nanofactory",
        "Forbidden Teleportation Experiment Site",
        "Time-Traveling Device Warehouse",
        "Forbidden AI Consciousness Experiment",
        "Dimensional Rift Stabilization Facility",
        "Hidden Particle Accelerator",
        "Forbidden Genetic Mutation Lab",
        "Stolen Military Weapon Arsenal",
        "Forbidden Virtual Reality Simulation",
        "Secret Satellite Weapon Control Center",
        "Biohazard Containment Facility",
        "Forbidden Neural Implant Lab",
        "Underground Nuclear Fusion Reactor",
        "Artificial Intelligence Virus Testing Lab",
        "Forbidden Pleasure-Simulating Chips Factory",
        "Molecular Distortion Experimentation Lab",
        "Stolen Biomechanical Combat Suits",
        "Forbidden Cybernetic Enhancement Lab",
        "Underground Exo-Suit Manufacturing Plant",
        "Forbidden Supercomputer Room",
        "Reality-Warping Weapon Testing Facility",
        "Memory-Modification Research Lab",
        "Forbidden Plasma Weapon Development Center",
        "Underground Stealth Technology Workshop",
        "Stolen Spacecraft Hangar",
        "Forbidden Sentient Robot Production Line",
        "Human Experimentation Facility",
        "Forbidden Duplication Device Lab",
        "Underground Force Field Generator",
        "Forbidden Bio-Organic Weapon Lab",
        "Secret Gene-Splicing Laboratory",
        "Reality-Bending Simulation Chamber",
        "Forbidden Cryogenic Preservation Facility",
        "Underground Mind-Control Experimentation Center"
    ],
    "SpaceAnomalies": [
        "Nebula of Whispering Echoes",
        "Pulsar with Encrypted Signals",
        "Black Hole at the End of Time",
        "Collapsing Star Matrix",
        "Quantum Entanglement Field",
        "Galactic Aurora Phenomenon",
        "Celestial Nebula of Shifting Colors",
        "Cosmic Radiation Storm",
        "Intergalactic Gravity Well",
        "Stellar Flare Burst",
        "Quasar Burst Anomaly",
        "Supernova Remnant",
        "Interstellar Dust Storm",
        "Celestial Void Singularity",
        "Astrological Zodiac Alignment",
        "Planetary Alignment Anomaly",
        "Celestial Plasma Implosion",
        "Dimensional Wormhole Rift",
        "Exoplanetary Auroral Storm",
        "Celestial Gravitational Lensing",
        "Interdimensional Time Vortex",
        "Space-Time Distortion Field",
        "Celestial Warp Bubble",
        "Star Collapse Phenomenon",
        "Quantum Teleportation Anomaly",
        "Luminous Spiral Galaxy Collision",
        "Celestial Time Dilation Effect",
        "Astrobiological Singularity",
        "Celestial Hyperspace Gateway",
        "Cosmic Quasar Repulsion",
        "Celestial Quasar Burst",
        "Astrological Supermoon Eclipse",
        "Celestial Stardust Ascension",
        "Cosmic Dark Matter Wave",
        "Celestial Wormhole Crossing",
        "Astrobiological Contagion",
        "Celestial Cosmic String",
        "Celestial Serpent Nebula",
        "Galactic Electromagnetic Wave",
        "Celestial Planetesimal Swarm",
        "Astrological Meteor Shower",
        "Celestial Plasma Rain",
        "Stellar Gravity Wave",
        "Astrobiological Resonance",
        "Celestial Time Portal",
        "Astrological Solar Flare",
        "Galactic Energy Burst",
        "Astrobiological Genesis Pulse",
        "Celestial Antipodal Convergence",
        "Quantum Entanglement Anomaly"
    ],
    "Erotic": [
        "Silk-canopied Bed",
        "Rooftop Garden under the Stars",
        "Secluded Beach Bungalow",
        "Candlelit Whirlpool Suite",
        "Heart-shaped Hot Tub Room",
        "Luxurious Honeymoon Suite",
        "Private Overwater Villa",
        "Sensual Spa Retreat",
        "Enchanted Rose Garden",
        "Moonlit Serenade Balcony",
        "Intimate Wine Cellar",
        "Boudoir with Velvet Drapes",
        "Twilight Mountain Cabin",
        "Isolated Island Getaway",
        "Lavish Yacht with Silk Sails",
        "Opulent Opera Box",
        "Mysterious Venetian Gondola",
        "Swan Lake Boathouse",
        "Sunset-View Cliffside Nest",
        "Blossom-Filled Courtyard",
        "Chateau De Amour",
        "Seductive Safari Tent",
        "French Quarter Jazz Lounge",
        "Cozy Fireplace Snug",
        "Baroque Castle Chamber",
        "Old Hollywood Glamour Hotel",
        "Victorian Carriage Ride",
        "Intricate Mirror Maze",
        "Misty Waterfall Grotto",
        "Arabian Nights Palace Room",
        "Dark Enchanted Forest Clearing",
        "Secret Dungeon Chamber",
        "Forbidden Temple Ruins",
        "Majestic Castle Tower",
        "Hidden Hot Spring Cove",
        "Luxury Penthouse with Panoramic Views",
        "Sultry Jazz Club Back Room",
        "Gothic Candlelit Cathedral",
        "Exotic Desert Oasis",
        "Seductive Underworld Speakeasy",
        "Abandoned Theatre Stage",
        "Velvet-lined Underground Cave",
        "Mirrored Ceiling Master Suite",
        "Lush Rainforest Waterfall",
        "Obsidian Coastline at Midnight",
        "Mystical Fairy Ring",
        "Victorian Widow's Walk",
        "Decadent Art Deco Boudoir",
        "Glimmering Bioluminescent Bay",
        "Imperial Asian Garden at Dusk",
        "Exclusive Masquerade Ball",
        "Old World Library with Hidden Passages",
        "Private Luxury Train Car",
        "Ritzy Casino's VIP Lounge",
        "Pirate's Secluded Cove",
        "Arctic Igloo under the Northern Lights",
        "Vine-entwined Pergola",
        "Stormy Cliff Overlook",
        "Speakeasy with a Secret Password",
        "Shrouded Moors with Abandoned Manor",
        "Enchanting Forest Glade",
        "Romantic Rooftop Retreat",
        "Hidden Cave of Passion",
        "Deserted Beach Hut",
        "Ethereal Moonlit Meadow",
        "Luxurious Paradise Island",
        "Secret Hideaway Cabin",
        "Charming Vineyard Cottage",
        "Seductive Lingerie Boutique",
        "Forbidden Love Sanctuary",
        "Intimate Treehouse Retreat",
        "Passionate Beach Bonfire",
        "Elegant Venetian Balcony",
        "Private Waterfall Oasis",
        "Enchanted Garden Pavilion",
        "Mystical Enclave of Desire",
        "Romantic Lakeside Cottage",
        "Hidden Romantic Rooftop Terrace",
        "Secluded Mountain Cabin",
        "Enigmatic Tropical Villa",
        "Sensual Couples Massage Studio",
        "Charming Tuscan Villa",
        "Seductive Silk Road Caravan",
        "Forbidden Love Nest",
        "Intimate Candlelit Wine Bar",
        "Private Seaside Retreat",
        "Enchanting Forest Glen",
        "Mystical Grotto of Passion",
        "Romantic Bed and Breakfast",
        "Hidden Rooftop Speakeasy",
        "Secluded Waterfall Swimming Hole",
        "Elegant Botanical Conservatory",
        "Passionate Dance Studio"
    ]
}